nat/__init__.py
nat/nat_amc_zynqup_sdr4.py
nat/nat_amc_zynqup_sdr8.py
pynat_iio-0.0.2.dist-info/LICENSE
pynat_iio-0.0.2.dist-info/METADATA
pynat_iio-0.0.2.dist-info/WHEEL
pynat_iio-0.0.2.dist-info/top_level.txt
pynat_iio-0.0.2.dist-info/RECORD
