Metadata-Version: 2.1
Name: pynat-iio
Version: 0.0.2
Summary: Interfaces to stream data from N.A.T. hardware
Home-page: https://github.com/NAT-GmbH/pynat-iio
Author: Thomas Florkowski
Author-email: thomas.florkowski@nateurope.com
License: UNKNOWN
Platform: UNKNOWN
Classifier: Programming Language :: Python :: 3
Classifier: License :: OSI Approved :: BSD License
Classifier: Operating System :: OS Independent
Requires-Python: >=3.6
License-File: LICENSE
Requires-Dist: pyadi-iio[jesd]
